{
  "$schema": "https://json-schema.org/draft/2019-09/schema",
  "description": "https://lua-api.factorio.com/stable/types/StatelessVisualisations.html",
  "anyOf": [
    {
      "$ref": "../split-schema/StatelessVisualisation.json"
    },
    {
      "oneOf": [
        {
          "type": "array",
          "items": {
            "anyOf": [
              {
                "$ref": "../split-schema/StatelessVisualisation.json"
              }
            ]
          }
        },
        {
          "type": "object",
          "additionalProperties": false
        }
      ]
    }
  ]
}